streamlit_copilot/__init__.py
streamlit_copilot/frontend/build/asset-manifest.json
streamlit_copilot/frontend/build/bootstrap.min.css
streamlit_copilot/frontend/build/index.html
streamlit_copilot/frontend/build/precache-manifest.5ee4a5ada856fc43a4760d446d0e8422.js
streamlit_copilot/frontend/build/service-worker.js
streamlit_copilot/frontend/build/static/js/2.232b3114.chunk.js
streamlit_copilot/frontend/build/static/js/2.232b3114.chunk.js.LICENSE.txt
streamlit_copilot/frontend/build/static/js/2.232b3114.chunk.js.map
streamlit_copilot/frontend/build/static/js/main.9652d827.chunk.js
streamlit_copilot/frontend/build/static/js/main.9652d827.chunk.js.map
streamlit_copilot/frontend/build/static/js/runtime-main.3b2d39e5.js
streamlit_copilot/frontend/build/static/js/runtime-main.3b2d39e5.js.map
streamlit_copilot-0.0.1.dist-info/LICENSE
streamlit_copilot-0.0.1.dist-info/METADATA
streamlit_copilot-0.0.1.dist-info/WHEEL
streamlit_copilot-0.0.1.dist-info/top_level.txt
streamlit_copilot-0.0.1.dist-info/RECORD
