Metadata-Version: 2.1
Name: streamlit-copilot
Version: 0.0.1
Summary: Streamlit component: Copilot text autocomplete
Home-page: https://github.com/sobkevich/streamlit-copilot
Requires-Python: >=3.6
License-File: LICENSE
Requires-Dist: streamlit (>=0.63)
